[
  {
    "id": 1,
    "index": "a79",
    "sourceName": "Oxford, BL Poc. 97, fol. 90v",
    "year": "1223",
    "writer": "שלמה בן שמואל הדיין הלוי",
    "place": "פוסטאט, מצרים",
    "writingStyle": "מזרחי",
    "images": {
      "scan": "scan-1.jpg",
      "digitization": "font-1.jpg"
    },
    "availableLetters": "אבהוטילמנ"
  },
  {
    "id": 2,
    "index": "a84",
    "sourceName": "Oxford, BL Poc. 135, fol. 28v",
    "year": "1277",
    "writer": "אליעזר בן אברהם",
    "place": "בעלבק, לבנון",
    "writingStyle": "מזרחי",
    "images": {
      "scan": "scan-2.jpg",
      "digitization": "font-2.jpg"
    },
    "availableLetters": "הילפרת"
  },
  {
    "id": 3,
    "index": "a125",
    "sourceName": "San Francisco, SL WPA 121, fol. 73v",
    "year": "1382",
    "writer": "לא ידוע",
    "place": "צנעא, תימן",
    "writingStyle": "תימני",
    "images": {
      "scan": "scan-3.jpg",
      "digitization": "font-3.jpg"
    },
    "availableLetters": "בוזיכלםמקש"
  },
  {
    "id": 4,
    "index": "a128",
    "sourceName": "Berlin, SB Ms. Or. 4 570, fol. 200v",
    "year": "1386",
    "writer": "לא ידוע",
    "place": "תימן",
    "writingStyle": "תימני",
    "images": {
      "scan": "scan-4.jpg",
      "digitization": "font-4.jpg"
    },
    "availableLetters": "וילמםקש"
  },
  {
    "id": 5,
    "index": "a141",
    "sourceName": "Jerusalem, AK, fol. 87v",
    "year": "1473",
    "writer": "דויד בן בניה בן סעדיה",
    "place": "צנעא, תימן",
    "writingStyle": "תימני",
    "images": {
      "scan": "scan-5.jpg",
      "digitization": "font-5.jpg"
    },
    "availableLetters": "דטילםןקרש"
  },
  {
    "id": 6,
    "index": "ms. 4038",
    "sourceName": "Strasbourg, Ms. 4038, fol. 2",
    "year": "לא ידוע",
    "writer": "לא ידוע",
    "place": "לא ידוע",
    "writingStyle": "תימני",
    "images": {
      "scan": "scan-6.jpg",
      "digitization": "font-6.jpg"
    },
    "availableLetters": "הוילנפצ"
  },
  {
    "id": 7,
    "index": "b80",
    "sourceName": "Oxford, BL Bodl. Or. 611, fol. 40v",
    "year": "1332",
    "writer": "יעקב בן משה בן אבי דינאר",
    "place": "פאס, מרוקו",
    "writingStyle": "ספרדי",
    "images": {
      "scan": "scan-7.jpg",
      "digitization": "font-7.jpg"
    },
    "availableLetters": "אהוטילמנש"
  },
  {
    "id": 8,
    "index": "b90",
    "sourceName": "Paris, BN hebr. 351, fol. 20v",
    "year": "1395",
    "writer": "אשטרוג שמייל כנסי",
    "place": "פרובנס, צרפת",
    "writingStyle": "ספרדי",
    "images": {
      "scan": "scan-8.jpg",
      "digitization": "font-8.jpg"
    },
    "availableLetters": "אוימןפצש"
  },
  {
    "id": 9,
    "index": "b92",
    "sourceName": "Oxford, BL Can. Or. 81, fol. 45v",
    "year": "1396",
    "writer": "מאיר בן שמואל מפוינצה",
    "place": "פישאה, איטליה",
    "writingStyle": "ספרדי",
    "images": {
      "scan": "scan-9.jpg",
      "digitization": "font-9.jpg"
    },
    "availableLetters": "אבויכסערת"
  },
  {
    "id": 10,
    "index": "b118",
    "sourceName": "Frankfurt, SUB Ms. hebr. 8 112, fol. 5v",
    "year": "1462",
    "writer": "נסים בן ראובן גירונדי",
    "place": "שלמנקה, ספרד",
    "writingStyle": "ספרדי",
    "images": {
      "scan": "scan-10.jpg",
      "digitization": "font-10.jpg"
    },
    "availableLetters": "אבהוימערפש"
  },
  {
    "id": 11,
    "index": "b120",
    "sourceName": "Vatican, BA Neof. 47, fol. 78r",
    "year": "1465",
    "writer": "משה בין מאיר ן׳ יחיון",
    "place": "היטה, ספרד",
    "writingStyle": "ספרדי",
    "images": {
      "scan": "scan-11.jpg",
      "digitization": "font-11.jpg"
    },
    "availableLetters": "אבוחימרש"
  },
  {
    "id": 12,
    "index": "c77",
    "sourceName": "Munich, BSB Cod. hebr. 5(2), fol. 27v",
    "year": "1232",
    "writer": "יוסף",
    "place": "גרמניה",
    "writingStyle": "אשכנזי",
    "images": {
      "scan": "scan-12.jpg",
      "digitization": "font-12.jpg"
    },
    "availableLetters": "אוילמרשת"
  },
  {
    "id": 13,
    "index": "c78",
    "sourceName": "Munich, BSB Cod. hebr. 5(2), fol. 120v",
    "year": "1233",
    "writer": "שלמה בן שמואל",
    "place": "גרמניה",
    "writingStyle": "אשכנזי",
    "images": {
      "scan": "scan-13.jpg",
      "digitization": "font-13.jpg"
    },
    "availableLetters": "גהויכםנש"
  },
  {
    "id": 14,
    "index": "c81",
    "sourceName": "London, BL Add. 27200, fol. 30v",
    "year": "1241",
    "writer": "שמעיה",
    "place": "צרפת",
    "writingStyle": "אשכנזי",
    "images": {
      "scan": "scan-14.jpg",
      "digitization": "font-14.jpg"
    },
    "availableLetters": "אוילערת"
  },
  {
    "id": 15,
    "index": "c154-a",
    "sourceName": "Hamburg, SUB Cod. hebr. 65, fol. 138v",
    "year": "1404",
    "writer": "נפטלי בן שלמה הלוי",
    "place": "לא ידוע",
    "writingStyle": "אשכנזי",
    "images": {
      "scan": "scan-15.jpg",
      "digitization": "font-15.jpg"
    },
    "availableLetters": "אהויכמצרש"
  },
  {
    "id": 16,
    "index": "c154-b",
    "sourceName": "Hamburg, SUB Cod. hebr. 65, fol. 138v",
    "year": "1404",
    "writer": "נפטלי בן שלמה הלוי",
    "place": "לא ידוע",
    "writingStyle": "אשכנזי",
    "images": {
      "scan": "scan-16.jpg",
      "digitization": "font-16.jpg"
    },
    "availableLetters": "אהוינסרת"
  },
  {
    "id": 17,
    "index": "c159-a",
    "sourceName": "Cod. Parm. 2180",
    "year": "1419",
    "writer": "לוי בן גרשם",
    "place": "סיינה, איטליה",
    "writingStyle": "אשכנזי",
    "images": {
      "scan": "scan-17.jpg",
      "digitization": "font-17.jpg"
    },
    "availableLetters": "אהילםמת"
  },
  {
    "id": 18,
    "index": "c159-b",
    "sourceName": "Cod. Parm. 2180",
    "year": "1419",
    "writer": "לוי בן גרשם",
    "place": "סיינה, איטליה",
    "writingStyle": "אשכנזי",
    "images": {
      "scan": "scan-18.jpg",
      "digitization": "font-18.jpg"
    },
    "availableLetters": "אבגהלםנעפת"
  }
]
